ostk/__init__.py
ostk/io/OpenSpaceToolkitIOPy.cpython-312-aarch64-linux-gnu.so
ostk/io/__init__.py
ostk/io/__init__.pyi
ostk/io/libopen-space-toolkit-io.so.4
ostk/io/ip/__init__.pyi
ostk/io/ip/tcp/__init__.pyi
ostk/io/ip/tcp/http.pyi
ostk/io/test/__init__.py
ostk/io/test/ip/__init__.py
ostk/io/test/ip/tcp/__init__.py
ostk/io/test/ip/tcp/http/__init__.py
ostk/io/test/ip/tcp/http/test_client.py
ostk/io/test/ip/tcp/http/test_request.py
ostk/io/test/ip/tcp/http/test_response.py
ostk/io/test/url/__init__.py
ostk/io/test/url/test_url.py
open_space_toolkit_io-4.1.1.dist-info/METADATA
open_space_toolkit_io-4.1.1.dist-info/WHEEL
open_space_toolkit_io-4.1.1.dist-info/top_level.txt
open_space_toolkit_io-4.1.1.dist-info/zip-safe
open_space_toolkit_io-4.1.1.dist-info/RECORD
