Metadata-Version: 2.2
Name: open-space-toolkit-io
Version: 4.1.1
Summary: Addressing, networking, database connectors.
Author: Open Space Collective
Author-email: contact@open-space-collective.org
License: Apache License 2.0
Keywords: open-space-collective,open-space-toolkit io
Classifier: Development Status :: 3 - Alpha
Classifier: Programming Language :: Python :: 3
Classifier: License :: OSI Approved :: Apache Software License
Classifier: Operating System :: POSIX :: Linux
Requires-Dist: open-space-toolkit-core~=5.0
